tests/__init__.py
tests/test_your_module.py
quay_api_client-0.0.1.dist-info/LICENSE
quay_api_client-0.0.1.dist-info/METADATA
quay_api_client-0.0.1.dist-info/WHEEL
quay_api_client-0.0.1.dist-info/top_level.txt
quay_api_client-0.0.1.dist-info/RECORD
